{
  "unpublishedCollection": {
    "name": "JSObject1",
    "pageId": "Cadastro Day Off",
    "pluginId": "js-plugin",
    "pluginType": "JS",
    "actions": [],
    "archivedActions": [],
    "body": "export default {\n\tupload_files: ['data'],\n\tmyVar2: {},\n\tmyFun1: () => {\n\t\t//write code here\n\t},\n\tmyFun2: async () => {\n\t\t//use async-await or promises\n\t}\n}\n\nconst buffer = buffer.from(rawData, 'base64');\nconst bufString = buffer.toString('hex');",
    "variables": [
      {
        "name": "upload_files",
        "value": "['data']"
      },
      {
        "name": "myVar2",
        "value": "{}"
      }
    ]
  },
  "id": "Cadastro Day Off_JSObject1",
  "deleted": false,
  "gitSyncId": "630d2361436de013c616dfb7_630e4bed40680c6837a949a6"
}